[{"rt":15889.314999920316,"stimulus":"\n    <p>This experiment uses your camera for eye tracking.</p>\n    <p>No video is saved from this experiment. The only data recorded are predictions about where you are looking.</p>\n    <p>Before we begin, there are a few things to do that can improve the accuracy of the eye tracking.</p>\n  ","response":0,"phase":"initial-calibration","trial_type":"html-button-response","trial_index":0,"time_elapsed":15892,"internal_node_id":"0.0-0.0-0.0","subject_id":"60142d5718e5943b09fd9298","study_id":"60623f75ce3a7bd372ac817b","session_id":"6085c3b4e17a3c6f79002088"},{"rt":18659.845000016503,"stimulus":"\n    <p>If you wear glasses and can complete the task without them, please remove your glasses.</p>\n    <p>If you need to keep your glasses on to read this text, you can leave them on.</p>\n  ","response":0,"phase":"initial-calibration","trial_type":"html-button-response","trial_index":1,"time_elapsed":34552,"internal_node_id":"0.0-0.0-1.0","subject_id":"60142d5718e5943b09fd9298","study_id":"60623f75ce3a7bd372ac817b","session_id":"6085c3b4e17a3c6f79002088"},{"rt":9356.32500005886,"stimulus":"\n    <p>Please close additional browser tabs and apps running in the background.</p>\n    <p>The eye tracker works best when there are fewer things running at the same time.</p>\n  ","response":0,"phase":"initial-calibration","trial_type":"html-button-response","trial_index":2,"time_elapsed":43909,"internal_node_id":"0.0-0.0-2.0","subject_id":"60142d5718e5943b09fd9298","study_id":"60623f75ce3a7bd372ac817b","session_id":"6085c3b4e17a3c6f79002088"},{"rt":11109.880000003614,"stimulus":"\n    <p>Try to avoid bright lights behind you.</p>\n    <p>The eye tracker works best if your face is well lit from the front.</p>\n    <p>If you can, adjust the lighting in your room.</p>\n  ","response":0,"phase":"initial-calibration","trial_type":"html-button-response","trial_index":3,"time_elapsed":55019,"internal_node_id":"0.0-0.0-3.0","subject_id":"60142d5718e5943b09fd9298","study_id":"60623f75ce3a7bd372ac817b","session_id":"6085c3b4e17a3c6f79002088"},{"rt":8881.134999915957,"stimulus":"\n    <p>Turn off anything that may produce an alert or notification during the task.</p>\n  ","response":0,"phase":"initial-calibration","trial_type":"html-button-response","trial_index":4,"time_elapsed":63901,"internal_node_id":"0.0-0.0-4.0","subject_id":"60142d5718e5943b09fd9298","study_id":"60623f75ce3a7bd372ac817b","session_id":"6085c3b4e17a3c6f79002088"},{"rt":16122.045000083745,"stimulus":"\n    <p>In order to participate you must allow the experiment to use your camera.</p>\n    <p>You will be prompted to do this on the next screen.</p>\n    <p>If you do not wish to allow use of your camera, you cannot participate in this experiment.<p>\n    <p>It may take up to 30 seconds for the camera to initialize after you give permission.</p>\n  ","response":0,"phase":"initial-calibration","trial_type":"html-button-response","trial_index":5,"time_elapsed":80024,"internal_node_id":"0.0-0.0-5.0","subject_id":"60142d5718e5943b09fd9298","study_id":"60623f75ce3a7bd372ac817b","session_id":"6085c3b4e17a3c6f79002088"},{"load_time":2661,"phase":"initial-calibration","trial_type":"webgazer-init-camera","trial_index":6,"time_elapsed":128453,"internal_node_id":"0.0-0.0-6.0","subject_id":"60142d5718e5943b09fd9298","study_id":"60623f75ce3a7bd372ac817b","session_id":"6085c3b4e17a3c6f79002088"},{"success":true,"phase":"initial-calibration","trial_type":"fullscreen","trial_index":7,"time_elapsed":132754,"internal_node_id":"0.0-0.0-7.0","subject_id":"60142d5718e5943b09fd9298","study_id":"60623f75ce3a7bd372ac817b","session_id":"6085c3b4e17a3c6f79002088"},{"rt":7251.264999969862,"stimulus":"\n    <p>Now you'll calibrate the eye tracking, so that the software can use the image of your eyes to predict where you are looking.</p>\n    <p>You'll see a series of dots appear on the screen. Look at each dot and click on it.</p>\n  ","response":0,"phase":"initial-calibration","trial_type":"html-button-response","trial_index":8,"time_elapsed":140006,"internal_node_id":"0.0-0.0-8.0","subject_id":"60142d5718e5943b09fd9298","study_id":"60623f75ce3a7bd372ac817b","session_id":"6085c3b4e17a3c6f79002088"},{"phase":"initial-calibration","trial_type":"webgazer-calibrate","trial_index":9,"time_elapsed":199772,"internal_node_id":"0.0-0.0-9.0","subject_id":"60142d5718e5943b09fd9298","study_id":"60623f75ce3a7bd372ac817b","session_id":"6085c3b4e17a3c6f79002088"},{"rt":13633.750000037253,"stimulus":"\n    <p>Now we'll measure the accuracy of the calibration.</p>\n    <p>Keep your head still, and move your eyes to look at the dots.</p>\n    <p>Please move your mouse to the corner of your screen so it does not distract you</p>\n    <p style=\"font-weight: bold;\">You do not need to click on the dots this time.</p>\n  ","response":0,"phase":"initial-calibration","trial_type":"html-button-response","trial_index":10,"time_elapsed":213407,"internal_node_id":"0.0-0.0-10.0","subject_id":"60142d5718e5943b09fd9298","study_id":"60623f75ce3a7bd372ac817b","session_id":"6085c3b4e17a3c6f79002088"},{"raw_gaze":[[{"x":458,"y":413,"dx":189.72500610351562,"dy":384.7250003814697,"t":831},{"x":406,"y":360,"dx":137.72500610351562,"dy":331.7250003814697,"t":1228},{"x":361,"y":263,"dx":92.72500610351562,"dy":234.72500038146973,"t":1624},{"x":338,"y":227,"dx":69.72500610351562,"dy":198.72500038146973,"t":2013},{"x":320,"y":169,"dx":51.725006103515625,"dy":140.72500038146973,"t":2399},{"x":306,"y":131,"dx":37.725006103515625,"dy":102.72500038146973,"t":2793}],[{"x":592,"y":-74,"dx":-697.7125244140625,"dy":-102.27499961853027,"t":3958},{"x":703,"y":-90,"dx":-586.7125244140625,"dy":-118.27499961853027,"t":4348},{"x":909,"y":-106,"dx":-380.7125244140625,"dy":-134.27499961853027,"t":4732},{"x":1114,"y":-118,"dx":-175.7125244140625,"dy":-146.27499961853027,"t":5120},{"x":1288,"y":-125,"dx":-1.7125244140625,"dy":-153.27499961853027,"t":5503},{"x":1363,"y":-151,"dx":73.2874755859375,"dy":-179.27499961853027,"t":5893}],[{"x":1079,"y":296,"dx":810.7250061035156,"dy":-535.7999877929688,"t":7044},{"x":889,"y":449,"dx":620.7250061035156,"dy":-382.79998779296875,"t":7446},{"x":756,"y":585,"dx":487.7250061035156,"dy":-246.79998779296875,"t":8022},{"x":632,"y":699,"dx":363.7250061035156,"dy":-132.79998779296875,"t":8470},{"x":505,"y":761,"dx":236.72500610351562,"dy":-70.79998779296875,"t":8890}],[{"x":699,"y":874,"dx":-590.7125244140625,"dy":42.20001220703125,"t":10154},{"x":862,"y":898,"dx":-427.7125244140625,"dy":66.20001220703125,"t":10563},{"x":1014,"y":910,"dx":-275.7125244140625,"dy":78.20001220703125,"t":10982},{"x":1132,"y":942,"dx":-157.7125244140625,"dy":110.20001220703125,"t":11396},{"x":1210,"y":931,"dx":-79.7125244140625,"dy":99.20001220703125,"t":11959}],[{"x":905,"y":679,"dx":527.2875061035156,"dy":443.3625030517578,"t":13116},{"x":760,"y":576,"dx":382.2875061035156,"dy":340.3625030517578,"t":13504},{"x":610,"y":503,"dx":232.28750610351562,"dy":267.3625030517578,"t":13883},{"x":515,"y":440,"dx":137.28750610351562,"dy":204.3625030517578,"t":14262},{"x":418,"y":375,"dx":40.287506103515625,"dy":139.3625030517578,"t":14639},{"x":370,"y":347,"dx":-7.712493896484375,"dy":111.36250305175781,"t":15011}],[{"x":512,"y":299,"dx":-522.3500366210938,"dy":63.36250305175781,"t":16142},{"x":644,"y":214,"dx":-390.35003662109375,"dy":-21.637496948242188,"t":16519},{"x":799,"y":202,"dx":-235.35003662109375,"dy":-33.63749694824219,"t":16892},{"x":918,"y":143,"dx":-116.35003662109375,"dy":-92.63749694824219,"t":17284},{"x":946,"y":151,"dx":-88.35003662109375,"dy":-84.63749694824219,"t":17865},{"x":955,"y":84,"dx":-79.35003662109375,"dy":-151.6374969482422,"t":18318}],[{"x":767,"y":324,"dx":389.2875061035156,"dy":-313.4000244140625,"t":19572},{"x":647,"y":371,"dx":269.2875061035156,"dy":-266.4000244140625,"t":19980},{"x":531,"y":422,"dx":153.28750610351562,"dy":-215.4000244140625,"t":20395},{"x":460,"y":481,"dx":82.28750610351562,"dy":-156.4000244140625,"t":20810},{"x":403,"y":540,"dx":25.287506103515625,"dy":-97.4000244140625,"t":21219},{"x":331,"y":570,"dx":-46.712493896484375,"dy":-67.4000244140625,"t":21630}],[{"x":607,"y":617,"dx":-427.35003662109375,"dy":-20.4000244140625,"t":22870},{"x":722,"y":661,"dx":-312.35003662109375,"dy":23.5999755859375,"t":23280},{"x":782,"y":654,"dx":-252.35003662109375,"dy":16.5999755859375,"t":23691},{"x":878,"y":699,"dx":-156.35003662109375,"dy":61.5999755859375,"t":24100},{"x":925,"y":716,"dx":-109.35003662109375,"dy":78.5999755859375,"t":24517},{"x":965,"y":720,"dx":-69.35003662109375,"dy":82.5999755859375,"t":24927}],[{"x":992,"y":675,"dx":213,"dy":232,"t":26154},{"x":859,"y":530,"dx":80,"dy":87,"t":26568},{"x":844,"y":493,"dx":65,"dy":50,"t":26977},{"x":787,"y":393,"dx":8,"dy":-50,"t":27389},{"x":752,"y":373,"dx":-27,"dy":-70,"t":27796},{"x":736,"y":390,"dx":-43,"dy":-53,"t":28212}]],"percent_in_roi":[33.33333333333333,33.33333333333333,0,40,33.33333333333333,50,50,50,83.33333333333334],"average_offset":[{"x":96.55833943684895,"y":232.22500038146973,"r":155.7333747592357},{"x":-294.8791910807292,"y":-138.94166628519693,"r":439.32261349005483},{"x":503.9250061035156,"y":-273.79998779296875,"r":198.83923154146416},{"x":-306.3125244140625,"y":79.20001220703125,"r":151.79907773105873},{"x":218.62083943684897,"y":251.02916971842447,"r":291.6645333730865},{"x":-238.6833699544271,"y":-53.47083028157552,"r":231.01574344021762},{"x":145.45417277018228,"y":-186.06669108072916,"r":222.27700362445233},{"x":-221.1833699544271,"y":40.433308919270836,"r":151.79111681862562},{"x":49.333333333333336,"y":32.666666666666664,"r":155.40077012761924}],"validation_points":[[15,2],[85,2],[15,95],[85,95],[22.5,26],[67.5,26],[22.5,72.5],[67.5,72.5],[50,50]],"samples_per_sec":"2.41","phase":"initial-calibration","task":"validate","trial_type":"webgazer-validate","trial_index":11,"time_elapsed":243046,"internal_node_id":"0.0-0.0-11.0","subject_id":"60142d5718e5943b09fd9298","study_id":"60623f75ce3a7bd372ac817b","session_id":"6085c3b4e17a3c6f79002088"},{"rt":7403.90999999363,"stimulus":"\n    <p>The accuracy of the calibration is a little lower than we'd like.</p>\n    <p>Let's try calibrating one more time.</p>\n    <p>Keep your head still, look at the dots, and click on them.<p>\n  ","response":0,"phase":"recalibration","trial_type":"html-button-response","trial_index":12,"time_elapsed":250451,"internal_node_id":"0.0-0.0-12.0-0.0","subject_id":"60142d5718e5943b09fd9298","study_id":"60623f75ce3a7bd372ac817b","session_id":"6085c3b4e17a3c6f79002088"},{"phase":"recalibration","trial_type":"webgazer-calibrate","trial_index":13,"time_elapsed":314371,"internal_node_id":"0.0-0.0-12.0-1.0","subject_id":"60142d5718e5943b09fd9298","study_id":"60623f75ce3a7bd372ac817b","session_id":"6085c3b4e17a3c6f79002088"},{"rt":7041.5600000415,"stimulus":"\n    <p>Now we'll measure the accuracy of the calibration.</p>\n    <p>Keep your head still, and move your eyes to look at the dots.</p>\n    <p>Please move your mouse to the corner of your screen so it does not distract you</p>\n    <p style=\"font-weight: bold;\">You do not need to click on the dots this time.</p>\n  ","response":0,"phase":"recalibration","trial_type":"html-button-response","trial_index":14,"time_elapsed":321414,"internal_node_id":"0.0-0.0-12.0-2.0","subject_id":"60142d5718e5943b09fd9298","study_id":"60623f75ce3a7bd372ac817b","session_id":"6085c3b4e17a3c6f79002088"},{"raw_gaze":[[{"x":614,"y":235,"dx":345.7250061035156,"dy":206.72500038146973,"t":813},{"x":492,"y":177,"dx":223.72500610351562,"dy":148.72500038146973,"t":1190},{"x":414,"y":110,"dx":145.72500610351562,"dy":81.72500038146973,"t":1572},{"x":338,"y":51,"dx":69.72500610351562,"dy":22.725000381469727,"t":1951},{"x":293,"y":40,"dx":24.725006103515625,"dy":11.725000381469727,"t":2335},{"x":230,"y":-5,"dx":-38.274993896484375,"dy":-33.27499961853027,"t":2722}],[{"x":755,"y":-92,"dx":-534.7125244140625,"dy":-120.27499961853027,"t":3860},{"x":1010,"y":-98,"dx":-279.7125244140625,"dy":-126.27499961853027,"t":4258},{"x":1175,"y":-173,"dx":-114.7125244140625,"dy":-201.27499961853027,"t":4637},{"x":1297,"y":-191,"dx":7.2874755859375,"dy":-219.27499961853027,"t":5020},{"x":1432,"y":-186,"dx":142.2874755859375,"dy":-214.27499961853027,"t":5398},{"x":1528,"y":-108,"dx":238.2874755859375,"dy":-136.27499961853027,"t":5781}],[{"x":1130,"y":221,"dx":861.7250061035156,"dy":-610.7999877929688,"t":6936},{"x":937,"y":402,"dx":668.7250061035156,"dy":-429.79998779296875,"t":7316},{"x":771,"y":530,"dx":502.7250061035156,"dy":-301.79998779296875,"t":7694},{"x":681,"y":636,"dx":412.7250061035156,"dy":-195.79998779296875,"t":8077},{"x":531,"y":724,"dx":262.7250061035156,"dy":-107.79998779296875,"t":8455},{"x":451,"y":754,"dx":182.72500610351562,"dy":-77.79998779296875,"t":8834}],[{"x":694,"y":900,"dx":-595.7125244140625,"dy":68.20001220703125,"t":9974},{"x":801,"y":929,"dx":-488.7125244140625,"dy":97.20001220703125,"t":10351},{"x":892,"y":944,"dx":-397.7125244140625,"dy":112.20001220703125,"t":10730},{"x":941,"y":922,"dx":-348.7125244140625,"dy":90.20001220703125,"t":11108},{"x":994,"y":857,"dx":-295.7125244140625,"dy":25.20001220703125,"t":11485},{"x":1035,"y":798,"dx":-254.7125244140625,"dy":-33.79998779296875,"t":11885}],[{"x":806,"y":596,"dx":428.2875061035156,"dy":360.3625030517578,"t":13016},{"x":634,"y":412,"dx":256.2875061035156,"dy":176.3625030517578,"t":13403},{"x":498,"y":318,"dx":120.28750610351562,"dy":82.36250305175781,"t":13787},{"x":401,"y":275,"dx":23.287506103515625,"dy":39.36250305175781,"t":14163},{"x":311,"y":217,"dx":-66.71249389648438,"dy":-18.637496948242188,"t":14538},{"x":218,"y":150,"dx":-159.71249389648438,"dy":-85.63749694824219,"t":14913}],[{"x":440,"y":105,"dx":-594.3500366210938,"dy":-130.6374969482422,"t":16053},{"x":560,"y":129,"dx":-474.35003662109375,"dy":-106.63749694824219,"t":16428},{"x":656,"y":137,"dx":-378.35003662109375,"dy":-98.63749694824219,"t":16803},{"x":762,"y":134,"dx":-272.35003662109375,"dy":-101.63749694824219,"t":17177},{"x":870,"y":120,"dx":-164.35003662109375,"dy":-115.63749694824219,"t":17561},{"x":892,"y":149,"dx":-142.35003662109375,"dy":-86.63749694824219,"t":17937}],[{"x":717,"y":363,"dx":339.2875061035156,"dy":-274.4000244140625,"t":19070},{"x":587,"y":384,"dx":209.28750610351562,"dy":-253.4000244140625,"t":19462},{"x":471,"y":456,"dx":93.28750610351562,"dy":-181.4000244140625,"t":19838},{"x":390,"y":446,"dx":12.287506103515625,"dy":-191.4000244140625,"t":20213},{"x":318,"y":499,"dx":-59.712493896484375,"dy":-138.4000244140625,"t":20592},{"x":312,"y":535,"dx":-65.71249389648438,"dy":-102.4000244140625,"t":20975}],[{"x":596,"y":709,"dx":-438.35003662109375,"dy":71.5999755859375,"t":22124},{"x":691,"y":690,"dx":-343.35003662109375,"dy":52.5999755859375,"t":22498},{"x":765,"y":710,"dx":-269.35003662109375,"dy":72.5999755859375,"t":22874},{"x":820,"y":687,"dx":-214.35003662109375,"dy":49.5999755859375,"t":23256},{"x":878,"y":688,"dx":-156.35003662109375,"dy":50.5999755859375,"t":23804},{"x":887,"y":672,"dx":-147.35003662109375,"dy":34.5999755859375,"t":24201}],[{"x":863,"y":667,"dx":84,"dy":224,"t":25345},{"x":882,"y":627,"dx":103,"dy":184,"t":25731},{"x":844,"y":556,"dx":65,"dy":113,"t":26121},{"x":788,"y":510,"dx":9,"dy":67,"t":26501},{"x":801,"y":503,"dx":22,"dy":60,"t":26885},{"x":808,"y":461,"dx":29,"dy":18,"t":27267}]],"percent_in_roi":[66.66666666666666,0,16.666666666666664,0,66.66666666666666,16.666666666666664,50,33.33333333333333,66.66666666666666],"average_offset":[{"x":128.55833943684897,"y":73.05833371480306,"r":181.3858471090821},{"x":-90.2125244140625,"y":-169.60833295186362,"r":312.76727258400354},{"x":481.8916727701823,"y":-287.29998779296875,"r":376.6202783366436},{"x":-396.8791910807292,"y":59.866678873697914,"r":152.6026481677317},{"x":100.28750610351562,"y":92.36250305175781,"r":277.44003309298864},{"x":-337.68336995442706,"y":-106.63749694824219,"r":223.45008162085657},{"x":88.12083943684895,"y":-190.23335774739584,"r":214.97174797881704},{"x":-261.51670328776044,"y":55.266642252604164,"r":134.51184810098053},{"x":52,"y":111,"r":106.04762738287447}],"validation_points":[[15,2],[85,2],[15,95],[85,95],[22.5,26],[67.5,26],[22.5,72.5],[67.5,72.5],[50,50]],"samples_per_sec":"2.60","phase":"recalibration","task":"validate","trial_type":"webgazer-validate","trial_index":15,"time_elapsed":350084,"internal_node_id":"0.0-0.0-12.0-3.0","subject_id":"60142d5718e5943b09fd9298","study_id":"60623f75ce3a7bd372ac817b","session_id":"6085c3b4e17a3c6f79002088"},{"rt":4007.549999980256,"stimulus":"\n    <p>Great, we're done with calibration!</p>\n    <p>Remember to keep your head still as you continue to the experiment.</p>\n  ","response":0,"phase":"initial-calibration","trial_type":"html-button-response","trial_index":16,"time_elapsed":354093,"internal_node_id":"0.0-0.0-13.0","subject_id":"60142d5718e5943b09fd9298","study_id":"60623f75ce3a7bd372ac817b","session_id":"6085c3b4e17a3c6f79002088"},{"success":true,"timeout":false,"failed_images":[],"failed_audio":[],"failed_video":[],"trial_type":"preload","trial_index":17,"time_elapsed":362860,"internal_node_id":"0.0-1.0","subject_id":"60142d5718e5943b09fd9298","study_id":"60623f75ce3a7bd372ac817b","session_id":"6085c3b4e17a3c6f79002088"},{"rt":30496.225000009872,"stimulus":"\n        <div style=\"text-align:center\"><p>In this experiment, different scenes will appear in the center \n        of the screen alongside a voice recording that will be played.</p>\n        <p>If the spoken sentence is applicable to the accompanying scene, \n        press the letter F on the keyboard.</p>\n        <p>If the scene seems to not be applicable, press the letter J.</p>             \n        <p>Press any key to begin.</p></div>\n       \n      ","response":"f","trial_type":"html-keyboard-response","trial_index":18,"time_elapsed":393356,"internal_node_id":"0.0-2.0","subject_id":"60142d5718e5943b09fd9298","study_id":"60623f75ce3a7bd372ac817b","session_id":"6085c3b4e17a3c6f79002088"},{"trial_type":"call-function","trial_index":19,"time_elapsed":395358,"internal_node_id":"0.0-3.0","subject_id":"60142d5718e5943b09fd9298","study_id":"60623f75ce3a7bd372ac817b","session_id":"6085c3b4e17a3c6f79002088"},{"rt":7883.930000010878,"stimulus":"\n          <p>Here is trial 1.\n          </p> <p>Listen to the sentence: is that sentence possible with the image you see on the screen?</p>\n          <p style=\"text-align:center\">F for possible, J for not possible.</p>\n          <p style=\"text-align:center\">Press any key to begin.</p>\n          ","response":" ","trial_type":"html-keyboard-response","trial_index":20,"time_elapsed":403242,"internal_node_id":"0.0-4.0","subject_id":"60142d5718e5943b09fd9298","study_id":"60623f75ce3a7bd372ac817b","session_id":"6085c3b4e17a3c6f79002088"},{"rt":3069.333333333333,"stimulus":"audio/1t.mp3","response":"j","trial_type":"audio-keyboard-response","trial_index":21,"time_elapsed":408212,"internal_node_id":"0.0-5.0","subject_id":"60142d5718e5943b09fd9298","study_id":"60623f75ce3a7bd372ac817b","session_id":"6085c3b4e17a3c6f79002088","correct":false},{"rt":5042.155000031926,"stimulus":"<p> <strong> Good Job! </strong> </p> <p> There is no fireplace, so it is not possible for the person to light the fire. We will have one more trial.</p><p>Press any key to continue</p>","response":" ","trial_type":"html-keyboard-response","trial_index":22,"time_elapsed":413255,"internal_node_id":"0.0-6.0","subject_id":"60142d5718e5943b09fd9298","study_id":"60623f75ce3a7bd372ac817b","session_id":"6085c3b4e17a3c6f79002088"},{"rt":2933.6899999761954,"stimulus":"\n          <p>Here is trial 2.\n          </p> <p>Listen to the sentence: is that sentence possible with the image you see on the screen?</p>\n          <p style=\"text-align:center\">Press any key to begin.</p>\n          ","response":" ","trial_type":"html-keyboard-response","trial_index":23,"time_elapsed":416188,"internal_node_id":"0.0-7.0","subject_id":"60142d5718e5943b09fd9298","study_id":"60623f75ce3a7bd372ac817b","session_id":"6085c3b4e17a3c6f79002088"},{"rt":4930.666666666667,"stimulus":"audio/2t.mp3","response":"f","trial_type":"audio-keyboard-response","trial_index":24,"time_elapsed":422123,"internal_node_id":"0.0-8.0","subject_id":"60142d5718e5943b09fd9298","study_id":"60623f75ce3a7bd372ac817b","session_id":"6085c3b4e17a3c6f79002088","correct":true},{"rt":6804.340000031516,"stimulus":"<p> <strong> Good Job! </strong> </p><p> There is a postman and the postman can ride the bike. Now that you understand, we will continue with the experiment. Please remember to keep your head as still as possible </p><p>Press any key to continue</p>","response":" ","trial_type":"html-keyboard-response","trial_index":25,"time_elapsed":428927,"internal_node_id":"0.0-9.0","subject_id":"60142d5718e5943b09fd9298","study_id":"60623f75ce3a7bd372ac817b","session_id":"6085c3b4e17a3c6f79002088"},{"rt":5229.333333333329,"stimulus":"audio/12nr.mp3","response":"j","verb_type":"non-restricting","trial_type":"audio-keyboard-response","trial_index":26,"time_elapsed":436159,"internal_node_id":"0.0-10.0-0.0","subject_id":"60142d5718e5943b09fd9298","study_id":"60623f75ce3a7bd372ac817b","session_id":"6085c3b4e17a3c6f79002088","webgazer_data":[{"x":719,"y":429,"t":0},{"x":682,"y":478,"t":586},{"x":688,"y":529,"t":1016},{"x":636,"y":580,"t":1416},{"x":702,"y":638,"t":1828},{"x":770,"y":568,"t":2233},{"x":824,"y":645,"t":2634},{"x":730,"y":652,"t":3041},{"x":790,"y":624,"t":3613},{"x":747,"y":718,"t":4035},{"x":761,"y":838,"t":4434},{"x":721,"y":896,"t":4831}],"webgazer_targets":{"#scenes":{"x":249.60000610351562,"y":13.27500057220459,"width":1036.800048828125,"height":829.4375,"top":13.27500057220459,"right":1286.4000549316406,"bottom":842.7125005722046,"left":249.60000610351562}}},{"rt":6810.666666666677,"stimulus":"audio/8nr.mp3","response":"f","verb_type":"non-restricting","trial_type":"audio-keyboard-response","trial_index":27,"time_elapsed":443975,"internal_node_id":"0.0-10.0-0.1","subject_id":"60142d5718e5943b09fd9298","study_id":"60623f75ce3a7bd372ac817b","session_id":"6085c3b4e17a3c6f79002088","webgazer_data":[{"x":740,"y":905,"t":0},{"x":730,"y":881,"t":407},{"x":722,"y":813,"t":809},{"x":732,"y":784,"t":1207},{"x":685,"y":678,"t":1604},{"x":781,"y":631,"t":2005},{"x":792,"y":617,"t":2401},{"x":626,"y":522,"t":2799},{"x":645,"y":641,"t":3197},{"x":722,"y":701,"t":3610},{"x":800,"y":672,"t":4005},{"x":862,"y":629,"t":4400},{"x":985,"y":669,"t":4802},{"x":1014,"y":626,"t":5210},{"x":973,"y":632,"t":5620},{"x":932,"y":653,"t":6020},{"x":938,"y":632,"t":6414}],"webgazer_targets":{"#scenes":{"x":249.60000610351562,"y":13.27500057220459,"width":1036.800048828125,"height":829.4375,"top":13.27500057220459,"right":1286.4000549316406,"bottom":842.7125005722046,"left":249.60000610351562}}},{"rt":3578.6666666666633,"stimulus":"audio/9f.mp3","response":"f","verb_type":"NA","trial_type":"audio-keyboard-response","trial_index":28,"time_elapsed":448561,"internal_node_id":"0.0-10.0-0.2","subject_id":"60142d5718e5943b09fd9298","study_id":"60623f75ce3a7bd372ac817b","session_id":"6085c3b4e17a3c6f79002088","webgazer_data":[{"x":908,"y":623,"t":0},{"x":938,"y":647,"t":403},{"x":899,"y":640,"t":807},{"x":879,"y":593,"t":1199},{"x":769,"y":526,"t":1596},{"x":684,"y":569,"t":2002},{"x":809,"y":637,"t":2394},{"x":673,"y":588,"t":2792},{"x":591,"y":607,"t":3189}],"webgazer_targets":{"#scenes":{"x":249.60000610351562,"y":13.27500057220459,"width":1036.800048828125,"height":829.4375,"top":13.27500057220459,"right":1286.4000549316406,"bottom":842.7125005722046,"left":249.60000610351562}}},{"rt":3589.333333333329,"stimulus":"audio/9r.mp3","response":"f","verb_type":"restricting","trial_type":"audio-keyboard-response","trial_index":29,"time_elapsed":453169,"internal_node_id":"0.0-10.0-0.3","subject_id":"60142d5718e5943b09fd9298","study_id":"60623f75ce3a7bd372ac817b","session_id":"6085c3b4e17a3c6f79002088","webgazer_data":[{"x":608,"y":641,"t":0},{"x":627,"y":579,"t":398},{"x":615,"y":586,"t":812},{"x":551,"y":551,"t":1215},{"x":589,"y":472,"t":1608},{"x":545,"y":500,"t":2000},{"x":498,"y":501,"t":2405},{"x":530,"y":495,"t":2797},{"x":583,"y":399,"t":3196}],"webgazer_targets":{"#scenes":{"x":249.60000610351562,"y":13.27500057220459,"width":1036.800048828125,"height":829.4375,"top":13.27500057220459,"right":1286.4000549316406,"bottom":842.7125005722046,"left":249.60000610351562}}},{"rt":3978.6666666666547,"stimulus":"audio/14f.mp3","response":"j","verb_type":"NA","trial_type":"audio-keyboard-response","trial_index":30,"time_elapsed":458156,"internal_node_id":"0.0-10.0-0.4","subject_id":"60142d5718e5943b09fd9298","study_id":"60623f75ce3a7bd372ac817b","session_id":"6085c3b4e17a3c6f79002088","webgazer_data":[{"x":650,"y":448,"t":0},{"x":701,"y":510,"t":393},{"x":727,"y":571,"t":792},{"x":775,"y":602,"t":1193},{"x":908,"y":695,"t":1592},{"x":870,"y":675,"t":1986},{"x":770,"y":679,"t":2379},{"x":767,"y":551,"t":2777},{"x":662,"y":509,"t":3173},{"x":779,"y":651,"t":3576}],"webgazer_targets":{"#scenes":{"x":249.60000610351562,"y":13.27500057220459,"width":1036.800048828125,"height":829.4375,"top":13.27500057220459,"right":1286.4000549316406,"bottom":842.7125005722046,"left":249.60000610351562}}},{"rt":3149.3333333333453,"stimulus":"audio/4f.mp3","response":"j","verb_type":"NA","trial_type":"audio-keyboard-response","trial_index":31,"time_elapsed":462320,"internal_node_id":"0.0-10.0-0.5","subject_id":"60142d5718e5943b09fd9298","study_id":"60623f75ce3a7bd372ac817b","session_id":"6085c3b4e17a3c6f79002088","webgazer_data":[{"x":856,"y":656,"t":0},{"x":857,"y":648,"t":393},{"x":812,"y":652,"t":791},{"x":719,"y":569,"t":1183},{"x":743,"y":606,"t":1584},{"x":725,"y":548,"t":1980},{"x":739,"y":581,"t":2371},{"x":772,"y":579,"t":2762}],"webgazer_targets":{"#scenes":{"x":249.60000610351562,"y":13.27500057220459,"width":1036.800048828125,"height":829.4375,"top":13.27500057220459,"right":1286.4000549316406,"bottom":842.7125005722046,"left":249.60000610351562}}},{"rt":3578.6666666666633,"stimulus":"audio/5nr.mp3","response":"f","verb_type":"non-restricting","trial_type":"audio-keyboard-response","trial_index":32,"time_elapsed":466910,"internal_node_id":"0.0-10.0-0.6","subject_id":"60142d5718e5943b09fd9298","study_id":"60623f75ce3a7bd372ac817b","session_id":"6085c3b4e17a3c6f79002088","webgazer_data":[{"x":778,"y":509,"t":0},{"x":798,"y":557,"t":411},{"x":789,"y":546,"t":807},{"x":745,"y":547,"t":1198},{"x":773,"y":591,"t":1589},{"x":751,"y":517,"t":1991},{"x":813,"y":501,"t":2382},{"x":873,"y":443,"t":2793},{"x":877,"y":450,"t":3186}],"webgazer_targets":{"#scenes":{"x":249.60000610351562,"y":13.27500057220459,"width":1036.800048828125,"height":829.4375,"top":13.27500057220459,"right":1286.4000549316406,"bottom":842.7125005722046,"left":249.60000610351562}}},{"rt":3349.333333333334,"stimulus":"audio/1f.mp3","response":"j","verb_type":"NA","trial_type":"audio-keyboard-response","trial_index":33,"time_elapsed":471265,"internal_node_id":"0.0-10.0-0.7","subject_id":"60142d5718e5943b09fd9298","study_id":"60623f75ce3a7bd372ac817b","session_id":"6085c3b4e17a3c6f79002088","webgazer_data":[{"x":855,"y":466,"t":0},{"x":862,"y":475,"t":395},{"x":776,"y":440,"t":805},{"x":882,"y":529,"t":1369},{"x":773,"y":497,"t":1773},{"x":861,"y":549,"t":2168},{"x":711,"y":635,"t":2559},{"x":594,"y":676,"t":2952}],"webgazer_targets":{"#scenes":{"x":249.60000610351562,"y":13.27500057220459,"width":1036.800048828125,"height":829.4375,"top":13.27500057220459,"right":1286.4000549316406,"bottom":842.7125005722046,"left":249.60000610351562}}},{"rt":4349.333333333334,"stimulus":"audio/11nr.mp3","response":"f","verb_type":"non-restricting","trial_type":"audio-keyboard-response","trial_index":34,"time_elapsed":476630,"internal_node_id":"0.0-10.0-0.8","subject_id":"60142d5718e5943b09fd9298","study_id":"60623f75ce3a7bd372ac817b","session_id":"6085c3b4e17a3c6f79002088","webgazer_data":[{"x":681,"y":658,"t":0},{"x":743,"y":654,"t":404},{"x":749,"y":684,"t":799},{"x":812,"y":728,"t":1194},{"x":846,"y":732,"t":1582},{"x":893,"y":716,"t":1986},{"x":808,"y":664,"t":2377},{"x":859,"y":655,"t":2780},{"x":876,"y":555,"t":3171},{"x":819,"y":559,"t":3561},{"x":758,"y":556,"t":3960}],"webgazer_targets":{"#scenes":{"x":249.60000610351562,"y":13.27500057220459,"width":1036.800048828125,"height":829.4375,"top":13.27500057220459,"right":1286.4000549316406,"bottom":842.7125005722046,"left":249.60000610351562}}},{"rt":3149.333333333331,"stimulus":"audio/3nr.mp3","response":"f","verb_type":"non-restricting","trial_type":"audio-keyboard-response","trial_index":35,"time_elapsed":480791,"internal_node_id":"0.0-10.0-0.9","subject_id":"60142d5718e5943b09fd9298","study_id":"60623f75ce3a7bd372ac817b","session_id":"6085c3b4e17a3c6f79002088","webgazer_data":[{"x":788,"y":639,"t":0},{"x":823,"y":637,"t":394},{"x":835,"y":624,"t":790},{"x":942,"y":589,"t":1183},{"x":985,"y":569,"t":1583},{"x":863,"y":490,"t":1974},{"x":744,"y":546,"t":2364},{"x":583,"y":582,"t":2757}],"webgazer_targets":{"#scenes":{"x":249.60000610351562,"y":13.27500057220459,"width":1036.800048828125,"height":829.4375,"top":13.27500057220459,"right":1286.4000549316406,"bottom":842.7125005722046,"left":249.60000610351562}}},{"rt":3370.6666666666792,"stimulus":"audio/2r.mp3","response":"f","verb_type":"restricting","trial_type":"audio-keyboard-response","trial_index":36,"time_elapsed":485174,"internal_node_id":"0.0-10.0-0.10","subject_id":"60142d5718e5943b09fd9298","study_id":"60623f75ce3a7bd372ac817b","session_id":"6085c3b4e17a3c6f79002088","webgazer_data":[{"x":580,"y":575,"t":0},{"x":670,"y":632,"t":574},{"x":730,"y":572,"t":992},{"x":874,"y":636,"t":1388},{"x":895,"y":639,"t":1781},{"x":896,"y":656,"t":2182},{"x":859,"y":683,"t":2579},{"x":789,"y":671,"t":2975}],"webgazer_targets":{"#scenes":{"x":249.60000610351562,"y":13.27500057220459,"width":1036.800048828125,"height":829.4375,"top":13.27500057220459,"right":1286.4000549316406,"bottom":842.7125005722046,"left":249.60000610351562}}},{"rt":4061.333333333351,"stimulus":"audio/3f.mp3","response":"j","verb_type":"NA","trial_type":"audio-keyboard-response","trial_index":37,"time_elapsed":490244,"internal_node_id":"0.0-10.0-0.11","subject_id":"60142d5718e5943b09fd9298","study_id":"60623f75ce3a7bd372ac817b","session_id":"6085c3b4e17a3c6f79002088","webgazer_data":[{"x":801,"y":641,"t":0},{"x":833,"y":675,"t":392},{"x":817,"y":662,"t":805},{"x":755,"y":582,"t":1231},{"x":766,"y":582,"t":1655},{"x":711,"y":587,"t":2056},{"x":725,"y":539,"t":2455},{"x":737,"y":537,"t":2866},{"x":834,"y":622,"t":3262},{"x":839,"y":548,"t":3669}],"webgazer_targets":{"#scenes":{"x":249.60000610351562,"y":13.27500057220459,"width":1036.800048828125,"height":829.4375,"top":13.27500057220459,"right":1286.4000549316406,"bottom":842.7125005722046,"left":249.60000610351562}}},{"rt":4589.333333333343,"stimulus":"audio/11f.mp3","response":"j","verb_type":"NA","trial_type":"audio-keyboard-response","trial_index":38,"time_elapsed":495843,"internal_node_id":"0.0-10.0-0.12","subject_id":"60142d5718e5943b09fd9298","study_id":"60623f75ce3a7bd372ac817b","session_id":"6085c3b4e17a3c6f79002088","webgazer_data":[{"x":844,"y":651,"t":0},{"x":754,"y":602,"t":413},{"x":767,"y":602,"t":1003},{"x":866,"y":617,"t":1426},{"x":788,"y":682,"t":1818},{"x":806,"y":630,"t":2216},{"x":796,"y":600,"t":2610},{"x":937,"y":666,"t":3010},{"x":863,"y":687,"t":3408},{"x":881,"y":670,"t":3801},{"x":807,"y":545,"t":4192}],"webgazer_targets":{"#scenes":{"x":249.60000610351562,"y":13.27500057220459,"width":1036.800048828125,"height":829.4375,"top":13.27500057220459,"right":1286.4000549316406,"bottom":842.7125005722046,"left":249.60000610351562}}},{"rt":2938.666666666677,"stimulus":"audio/12f.mp3","response":"j","verb_type":"NA","trial_type":"audio-keyboard-response","trial_index":39,"time_elapsed":499786,"internal_node_id":"0.0-10.0-0.13","subject_id":"60142d5718e5943b09fd9298","study_id":"60623f75ce3a7bd372ac817b","session_id":"6085c3b4e17a3c6f79002088","webgazer_data":[{"x":786,"y":640,"t":0},{"x":784,"y":668,"t":394},{"x":740,"y":650,"t":795},{"x":628,"y":619,"t":1187},{"x":586,"y":605,"t":1579},{"x":747,"y":691,"t":1968},{"x":803,"y":730,"t":2369}],"webgazer_targets":{"#scenes":{"x":249.60000610351562,"y":13.27500057220459,"width":1036.800048828125,"height":829.4375,"top":13.27500057220459,"right":1286.4000549316406,"bottom":842.7125005722046,"left":249.60000610351562}}},{"rt":2981.3333333333103,"stimulus":"audio/7f.mp3","response":"j","verb_type":"NA","trial_type":"audio-keyboard-response","trial_index":40,"time_elapsed":503768,"internal_node_id":"0.0-10.0-0.14","subject_id":"60142d5718e5943b09fd9298","study_id":"60623f75ce3a7bd372ac817b","session_id":"6085c3b4e17a3c6f79002088","webgazer_data":[{"x":842,"y":671,"t":0},{"x":870,"y":686,"t":407},{"x":848,"y":673,"t":808},{"x":661,"y":651,"t":1199},{"x":706,"y":579,"t":1598},{"x":751,"y":609,"t":2173},{"x":629,"y":656,"t":2583}],"webgazer_targets":{"#scenes":{"x":249.60000610351562,"y":13.27500057220459,"width":1036.800048828125,"height":829.4375,"top":13.27500057220459,"right":1286.4000549316406,"bottom":842.7125005722046,"left":249.60000610351562}}},{"rt":3367.999999999995,"stimulus":"audio/1r.mp3","response":"f","verb_type":"restricting","trial_type":"audio-keyboard-response","trial_index":41,"time_elapsed":508148,"internal_node_id":"0.0-10.0-0.15","subject_id":"60142d5718e5943b09fd9298","study_id":"60623f75ce3a7bd372ac817b","session_id":"6085c3b4e17a3c6f79002088","webgazer_data":[{"x":653,"y":639,"t":0},{"x":731,"y":675,"t":404},{"x":667,"y":607,"t":971},{"x":706,"y":602,"t":1380},{"x":821,"y":636,"t":1772},{"x":740,"y":669,"t":2182},{"x":681,"y":702,"t":2573},{"x":675,"y":707,"t":2974}],"webgazer_targets":{"#scenes":{"x":249.60000610351562,"y":13.27500057220459,"width":1036.800048828125,"height":829.4375,"top":13.27500057220459,"right":1286.4000549316406,"bottom":842.7125005722046,"left":249.60000610351562}}},{"rt":8650.666666666666,"stimulus":"audio/7r.mp3","response":"j","verb_type":"restricting","trial_type":"audio-keyboard-response","trial_index":42,"time_elapsed":517803,"internal_node_id":"0.0-10.0-0.16","subject_id":"60142d5718e5943b09fd9298","study_id":"60623f75ce3a7bd372ac817b","session_id":"6085c3b4e17a3c6f79002088","webgazer_data":[{"x":785,"y":792,"t":0},{"x":787,"y":772,"t":392},{"x":759,"y":715,"t":786},{"x":790,"y":727,"t":1176},{"x":742,"y":744,"t":1572},{"x":680,"y":727,"t":1964},{"x":690,"y":702,"t":2353},{"x":616,"y":687,"t":2745},{"x":500,"y":689,"t":3136},{"x":484,"y":697,"t":3530},{"x":564,"y":651,"t":3922},{"x":670,"y":532,"t":4323},{"x":609,"y":508,"t":4714},{"x":557,"y":454,"t":5105},{"x":538,"y":490,"t":5511},{"x":545,"y":524,"t":5902},{"x":499,"y":566,"t":6290},{"x":613,"y":586,"t":6681},{"x":700,"y":498,"t":7070},{"x":578,"y":466,"t":7468},{"x":662,"y":467,"t":7863},{"x":746,"y":466,"t":8252}],"webgazer_targets":{"#scenes":{"x":249.60000610351562,"y":13.27500057220459,"width":1036.800048828125,"height":829.4375,"top":13.27500057220459,"right":1286.4000549316406,"bottom":842.7125005722046,"left":249.60000610351562}}},{"rt":3159.9999999999964,"stimulus":"audio/5f.mp3","response":"j","verb_type":"NA","trial_type":"audio-keyboard-response","trial_index":43,"time_elapsed":521964,"internal_node_id":"0.0-10.0-0.17","subject_id":"60142d5718e5943b09fd9298","study_id":"60623f75ce3a7bd372ac817b","session_id":"6085c3b4e17a3c6f79002088","webgazer_data":[{"x":834,"y":520,"t":0},{"x":874,"y":558,"t":392},{"x":942,"y":630,"t":801},{"x":984,"y":638,"t":1197},{"x":856,"y":700,"t":1589},{"x":814,"y":700,"t":1977},{"x":746,"y":723,"t":2371},{"x":633,"y":706,"t":2760}],"webgazer_targets":{"#scenes":{"x":249.60000610351562,"y":13.27500057220459,"width":1036.800048828125,"height":829.4375,"top":13.27500057220459,"right":1286.4000549316406,"bottom":842.7125005722046,"left":249.60000610351562}}},{"rt":5170.666666666648,"stimulus":"audio/10f.mp3","response":"f","verb_type":"NA","trial_type":"audio-keyboard-response","trial_index":44,"time_elapsed":528137,"internal_node_id":"0.0-10.0-0.18","subject_id":"60142d5718e5943b09fd9298","study_id":"60623f75ce3a7bd372ac817b","session_id":"6085c3b4e17a3c6f79002088","webgazer_data":[{"x":743,"y":664,"t":0},{"x":791,"y":624,"t":392},{"x":806,"y":514,"t":796},{"x":712,"y":519,"t":1201},{"x":518,"y":453,"t":1588},{"x":662,"y":508,"t":2003},{"x":740,"y":459,"t":2396},{"x":776,"y":425,"t":2791},{"x":728,"y":392,"t":3185},{"x":869,"y":478,"t":3574},{"x":971,"y":374,"t":3979},{"x":927,"y":349,"t":4374},{"x":790,"y":397,"t":4776}],"webgazer_targets":{"#scenes":{"x":249.60000610351562,"y":13.27500057220459,"width":1036.800048828125,"height":829.4375,"top":13.27500057220459,"right":1286.4000549316406,"bottom":842.7125005722046,"left":249.60000610351562}}},{"rt":4730.666666666679,"stimulus":"audio/6nr.mp3","response":"f","verb_type":"non-restricting","trial_type":"audio-keyboard-response","trial_index":45,"time_elapsed":533876,"internal_node_id":"0.0-10.0-0.19","subject_id":"60142d5718e5943b09fd9298","study_id":"60623f75ce3a7bd372ac817b","session_id":"6085c3b4e17a3c6f79002088","webgazer_data":[{"x":905,"y":559,"t":0},{"x":915,"y":579,"t":391},{"x":816,"y":486,"t":791},{"x":670,"y":451,"t":1181},{"x":595,"y":435,"t":1573},{"x":743,"y":462,"t":1963},{"x":862,"y":524,"t":2362},{"x":781,"y":518,"t":2756},{"x":747,"y":544,"t":3147},{"x":708,"y":549,"t":3549},{"x":594,"y":553,"t":3940},{"x":613,"y":577,"t":4333}],"webgazer_targets":{"#scenes":{"x":249.60000610351562,"y":13.27500057220459,"width":1036.800048828125,"height":829.4375,"top":13.27500057220459,"right":1286.4000549316406,"bottom":842.7125005722046,"left":249.60000610351562}}},{"rt":4338.666666666682,"stimulus":"audio/2f.mp3","response":"j","verb_type":"NA","trial_type":"audio-keyboard-response","trial_index":46,"time_elapsed":539230,"internal_node_id":"0.0-10.0-0.20","subject_id":"60142d5718e5943b09fd9298","study_id":"60623f75ce3a7bd372ac817b","session_id":"6085c3b4e17a3c6f79002088","webgazer_data":[{"x":675,"y":572,"t":0},{"x":766,"y":580,"t":401},{"x":806,"y":538,"t":801},{"x":813,"y":512,"t":1190},{"x":781,"y":555,"t":1582},{"x":670,"y":550,"t":1981},{"x":682,"y":636,"t":2371},{"x":681,"y":614,"t":2775},{"x":645,"y":562,"t":3164},{"x":652,"y":575,"t":3554},{"x":704,"y":603,"t":3952}],"webgazer_targets":{"#scenes":{"x":249.60000610351562,"y":13.27500057220459,"width":1036.800048828125,"height":829.4375,"top":13.27500057220459,"right":1286.4000549316406,"bottom":842.7125005722046,"left":249.60000610351562}}},{"rt":4930.666666666667,"stimulus":"audio/16r.mp3","response":"f","verb_type":"restricting","trial_type":"audio-keyboard-response","trial_index":47,"time_elapsed":545157,"internal_node_id":"0.0-10.0-0.21","subject_id":"60142d5718e5943b09fd9298","study_id":"60623f75ce3a7bd372ac817b","session_id":"6085c3b4e17a3c6f79002088","webgazer_data":[{"x":715,"y":582,"t":0},{"x":786,"y":575,"t":390},{"x":840,"y":615,"t":787},{"x":857,"y":632,"t":1178},{"x":870,"y":654,"t":1584},{"x":890,"y":636,"t":1976},{"x":898,"y":585,"t":2365},{"x":897,"y":562,"t":2755},{"x":762,"y":573,"t":3160},{"x":833,"y":625,"t":3723},{"x":921,"y":686,"t":4138},{"x":850,"y":655,"t":4531}],"webgazer_targets":{"#scenes":{"x":249.60000610351562,"y":13.27500057220459,"width":1036.800048828125,"height":829.4375,"top":13.27500057220459,"right":1286.4000549316406,"bottom":842.7125005722046,"left":249.60000610351562}}},{"rt":5338.666666666682,"stimulus":"audio/8f.mp3","response":"j","verb_type":"NA","trial_type":"audio-keyboard-response","trial_index":48,"time_elapsed":551503,"internal_node_id":"0.0-10.0-0.22","subject_id":"60142d5718e5943b09fd9298","study_id":"60623f75ce3a7bd372ac817b","session_id":"6085c3b4e17a3c6f79002088","webgazer_data":[{"x":816,"y":573,"t":0},{"x":850,"y":544,"t":395},{"x":808,"y":528,"t":799},{"x":831,"y":544,"t":1196},{"x":921,"y":571,"t":1598},{"x":853,"y":606,"t":1993},{"x":850,"y":499,"t":2396},{"x":752,"y":474,"t":2970},{"x":664,"y":489,"t":3379},{"x":536,"y":553,"t":3770},{"x":435,"y":527,"t":4163},{"x":451,"y":478,"t":4555},{"x":521,"y":448,"t":4949}],"webgazer_targets":{"#scenes":{"x":249.60000610351562,"y":13.27500057220459,"width":1036.800048828125,"height":829.4375,"top":13.27500057220459,"right":1286.4000549316406,"bottom":842.7125005722046,"left":249.60000610351562}}},{"rt":3280.000000000001,"stimulus":"audio/6f.mp3","response":"j","verb_type":"NA","trial_type":"audio-keyboard-response","trial_index":49,"time_elapsed":555784,"internal_node_id":"0.0-10.0-0.23","subject_id":"60142d5718e5943b09fd9298","study_id":"60623f75ce3a7bd372ac817b","session_id":"6085c3b4e17a3c6f79002088","webgazer_data":[{"x":543,"y":501,"t":0},{"x":586,"y":497,"t":428},{"x":591,"y":458,"t":857},{"x":528,"y":559,"t":1252},{"x":458,"y":465,"t":1662},{"x":457,"y":578,"t":2060},{"x":547,"y":604,"t":2466},{"x":632,"y":642,"t":2885}],"webgazer_targets":{"#scenes":{"x":249.60000610351562,"y":13.27500057220459,"width":1036.800048828125,"height":829.4375,"top":13.27500057220459,"right":1286.4000549316406,"bottom":842.7125005722046,"left":249.60000610351562}}},{"rt":3560.0000000000023,"stimulus":"audio/13f.mp3","response":"j","verb_type":"NA","trial_type":"audio-keyboard-response","trial_index":50,"time_elapsed":560348,"internal_node_id":"0.0-10.0-0.24","subject_id":"60142d5718e5943b09fd9298","study_id":"60623f75ce3a7bd372ac817b","session_id":"6085c3b4e17a3c6f79002088","webgazer_data":[{"x":655,"y":597,"t":0},{"x":747,"y":572,"t":420},{"x":799,"y":544,"t":816},{"x":909,"y":545,"t":1205},{"x":781,"y":506,"t":1603},{"x":818,"y":537,"t":1994},{"x":821,"y":429,"t":2389},{"x":756,"y":436,"t":2782},{"x":843,"y":500,"t":3170}],"webgazer_targets":{"#scenes":{"x":249.60000610351562,"y":13.27500057220459,"width":1036.800048828125,"height":829.4375,"top":13.27500057220459,"right":1286.4000549316406,"bottom":842.7125005722046,"left":249.60000610351562}}},{"rt":3799.9999999999827,"stimulus":"audio/13r.mp3","response":"f","verb_type":"restricting","trial_type":"audio-keyboard-response","trial_index":51,"time_elapsed":565142,"internal_node_id":"0.0-10.0-0.25","subject_id":"60142d5718e5943b09fd9298","study_id":"60623f75ce3a7bd372ac817b","session_id":"6085c3b4e17a3c6f79002088","webgazer_data":[{"x":897,"y":577,"t":0},{"x":868,"y":589,"t":401},{"x":863,"y":597,"t":980},{"x":756,"y":513,"t":1393},{"x":783,"y":519,"t":1790},{"x":823,"y":523,"t":2202},{"x":895,"y":557,"t":2594},{"x":884,"y":570,"t":3002},{"x":908,"y":561,"t":3398}],"webgazer_targets":{"#scenes":{"x":249.60000610351562,"y":13.27500057220459,"width":1036.800048828125,"height":829.4375,"top":13.27500057220459,"right":1286.4000549316406,"bottom":842.7125005722046,"left":249.60000610351562}}},{"rt":4570.666666666682,"stimulus":"audio/16f.mp3","response":"f","verb_type":"NA","trial_type":"audio-keyboard-response","trial_index":52,"time_elapsed":570712,"internal_node_id":"0.0-10.0-0.26","subject_id":"60142d5718e5943b09fd9298","study_id":"60623f75ce3a7bd372ac817b","session_id":"6085c3b4e17a3c6f79002088","webgazer_data":[{"x":967,"y":546,"t":0},{"x":951,"y":554,"t":565},{"x":923,"y":560,"t":982},{"x":833,"y":560,"t":1376},{"x":837,"y":572,"t":1777},{"x":740,"y":570,"t":2184},{"x":662,"y":583,"t":2585},{"x":769,"y":509,"t":2980},{"x":759,"y":532,"t":3375},{"x":719,"y":567,"t":3767},{"x":826,"y":558,"t":4163}],"webgazer_targets":{"#scenes":{"x":249.60000610351562,"y":13.27500057220459,"width":1036.800048828125,"height":829.4375,"top":13.27500057220459,"right":1286.4000549316406,"bottom":842.7125005722046,"left":249.60000610351562}}},{"rt":4759.999999999991,"stimulus":"audio/15nr.mp3","response":"f","verb_type":"non-restricting","trial_type":"audio-keyboard-response","trial_index":53,"time_elapsed":576487,"internal_node_id":"0.0-10.0-0.27","subject_id":"60142d5718e5943b09fd9298","study_id":"60623f75ce3a7bd372ac817b","session_id":"6085c3b4e17a3c6f79002088","webgazer_data":[{"x":934,"y":586,"t":0},{"x":1050,"y":716,"t":395},{"x":957,"y":755,"t":794},{"x":1007,"y":834,"t":1189},{"x":1014,"y":870,"t":1584},{"x":818,"y":840,"t":1986},{"x":748,"y":833,"t":2381},{"x":631,"y":917,"t":2775},{"x":604,"y":856,"t":3166},{"x":696,"y":818,"t":3563},{"x":660,"y":750,"t":3968},{"x":635,"y":681,"t":4360}],"webgazer_targets":{"#scenes":{"x":249.60000610351562,"y":13.27500057220459,"width":1036.800048828125,"height":829.4375,"top":13.27500057220459,"right":1286.4000549316406,"bottom":842.7125005722046,"left":249.60000610351562}}},{"rt":7589.333333333343,"stimulus":"audio/15f.mp3","response":"j","verb_type":"NA","trial_type":"audio-keyboard-response","trial_index":54,"time_elapsed":585090,"internal_node_id":"0.0-10.0-0.28","subject_id":"60142d5718e5943b09fd9298","study_id":"60623f75ce3a7bd372ac817b","session_id":"6085c3b4e17a3c6f79002088","webgazer_data":[{"x":655,"y":646,"t":0},{"x":722,"y":591,"t":392},{"x":735,"y":556,"t":799},{"x":666,"y":459,"t":1210},{"x":726,"y":415,"t":1616},{"x":754,"y":470,"t":2011},{"x":724,"y":496,"t":2407},{"x":762,"y":478,"t":2805},{"x":808,"y":518,"t":3215},{"x":796,"y":526,"t":3610},{"x":828,"y":550,"t":4002},{"x":971,"y":662,"t":4396},{"x":937,"y":666,"t":4796},{"x":958,"y":603,"t":5195},{"x":990,"y":526,"t":5591},{"x":1079,"y":463,"t":6003},{"x":1057,"y":501,"t":6403},{"x":1005,"y":500,"t":6798},{"x":1032,"y":442,"t":7197}],"webgazer_targets":{"#scenes":{"x":249.60000610351562,"y":13.27500057220459,"width":1036.800048828125,"height":829.4375,"top":13.27500057220459,"right":1286.4000549316406,"bottom":842.7125005722046,"left":249.60000610351562}}},{"rt":3968.0000000000177,"stimulus":"audio/10r.mp3","response":"f","verb_type":"restricting","trial_type":"audio-keyboard-response","trial_index":55,"time_elapsed":590065,"internal_node_id":"0.0-10.0-0.29","subject_id":"60142d5718e5943b09fd9298","study_id":"60623f75ce3a7bd372ac817b","session_id":"6085c3b4e17a3c6f79002088","webgazer_data":[{"x":1030,"y":526,"t":0},{"x":988,"y":579,"t":401},{"x":934,"y":578,"t":799},{"x":845,"y":576,"t":1193},{"x":846,"y":608,"t":1592},{"x":743,"y":697,"t":1986},{"x":701,"y":693,"t":2379},{"x":630,"y":696,"t":2778},{"x":613,"y":715,"t":3173},{"x":623,"y":723,"t":3570}],"webgazer_targets":{"#scenes":{"x":249.60000610351562,"y":13.27500057220459,"width":1036.800048828125,"height":829.4375,"top":13.27500057220459,"right":1286.4000549316406,"bottom":842.7125005722046,"left":249.60000610351562}}},{"rt":3570.6666666666533,"stimulus":"audio/4nr.mp3","response":"f","verb_type":"non-restricting","trial_type":"audio-keyboard-response","trial_index":56,"time_elapsed":594640,"internal_node_id":"0.0-10.0-0.30","subject_id":"60142d5718e5943b09fd9298","study_id":"60623f75ce3a7bd372ac817b","session_id":"6085c3b4e17a3c6f79002088","webgazer_data":[{"x":645,"y":810,"t":0},{"x":731,"y":742,"t":395},{"x":753,"y":638,"t":792},{"x":771,"y":597,"t":1188},{"x":670,"y":548,"t":1586},{"x":539,"y":462,"t":1990},{"x":442,"y":490,"t":2382},{"x":514,"y":495,"t":2781},{"x":440,"y":553,"t":3174}],"webgazer_targets":{"#scenes":{"x":249.60000610351562,"y":13.27500057220459,"width":1036.800048828125,"height":829.4375,"top":13.27500057220459,"right":1286.4000549316406,"bottom":842.7125005722046,"left":249.60000610351562}}},{"rt":4000,"stimulus":"audio/14r.mp3","response":"f","verb_type":"restricting","trial_type":"audio-keyboard-response","trial_index":57,"time_elapsed":599644,"internal_node_id":"0.0-10.0-0.31","subject_id":"60142d5718e5943b09fd9298","study_id":"60623f75ce3a7bd372ac817b","session_id":"6085c3b4e17a3c6f79002088","webgazer_data":[{"x":616,"y":574,"t":0},{"x":679,"y":568,"t":400},{"x":719,"y":571,"t":796},{"x":668,"y":495,"t":1189},{"x":750,"y":416,"t":1586},{"x":707,"y":425,"t":1984},{"x":790,"y":436,"t":2378},{"x":824,"y":435,"t":2774},{"x":842,"y":444,"t":3167},{"x":860,"y":437,"t":3567}],"webgazer_targets":{"#scenes":{"x":249.60000610351562,"y":13.27500057220459,"width":1036.800048828125,"height":829.4375,"top":13.27500057220459,"right":1286.4000549316406,"bottom":842.7125005722046,"left":249.60000610351562}}}]